graph_api/__init__.py
graph_api/base_element.py
graph_api/edge.py
graph_api/element_store.py
graph_api/fluent_query.py
graph_api/graph_query.py
graph_api/meta.py
graph_api/model_generator.py
graph_api/node.py
graph_api/rest_client.py
graph_api_python-0.4.2.dist-info/METADATA
graph_api_python-0.4.2.dist-info/WHEEL
graph_api_python-0.4.2.dist-info/licenses/LICENSE
graph_api_python-0.4.2.dist-info/RECORD
