Metadata-Version: 2.4
Name: graph-api-python
Version: 0.4.2
Summary: A fluent graph query library for Python with ElementStore and graph operations
Project-URL: Homepage, https://github.com/damylen/graph-api-python
Project-URL: Repository, https://github.com/damylen/graph-api-python
Project-URL: Documentation, https://github.com/damylen/graph-api-python#readme
Project-URL: Issues, https://github.com/damylen/graph-api-python/issues
Author-email: damylen <damylen@users.noreply.github.com>
License: MIT
License-File: LICENSE
Classifier: Development Status :: 4 - Beta
Classifier: Intended Audience :: Developers
Classifier: License :: OSI Approved :: MIT License
Classifier: Programming Language :: Python :: 3
Classifier: Programming Language :: Python :: 3.12
Requires-Python: >=3.12
Requires-Dist: httpx>=0.25.0
Requires-Dist: pydantic>=2.0.0
Provides-Extra: all
Requires-Dist: bandit[toml]>=1.7.0; extra == 'all'
Requires-Dist: black>=23.0; extra == 'all'
Requires-Dist: build>=1.0; extra == 'all'
Requires-Dist: coverage[toml]>=7.0; extra == 'all'
Requires-Dist: isort>=5.12; extra == 'all'
Requires-Dist: mypy>=1.0; extra == 'all'
Requires-Dist: pip-audit>=2.0.0; extra == 'all'
Requires-Dist: pre-commit>=3.0; extra == 'all'
Requires-Dist: pytest-asyncio>=0.21.0; extra == 'all'
Requires-Dist: pytest-cov>=4.0; extra == 'all'
Requires-Dist: pytest>=7.0; extra == 'all'
Requires-Dist: ruff>=0.1.0; extra == 'all'
Requires-Dist: safety>=2.0.0; extra == 'all'
Requires-Dist: twine>=4.0; extra == 'all'
Provides-Extra: dev
Requires-Dist: bandit[toml]>=1.7.0; extra == 'dev'
Requires-Dist: black>=23.0; extra == 'dev'
Requires-Dist: build>=1.0; extra == 'dev'
Requires-Dist: coverage[toml]>=7.0; extra == 'dev'
Requires-Dist: isort>=5.12; extra == 'dev'
Requires-Dist: mypy>=1.0; extra == 'dev'
Requires-Dist: pip-audit>=2.0.0; extra == 'dev'
Requires-Dist: pre-commit>=3.0; extra == 'dev'
Requires-Dist: pytest-asyncio>=0.21.0; extra == 'dev'
Requires-Dist: pytest-cov>=4.0; extra == 'dev'
Requires-Dist: pytest>=7.0; extra == 'dev'
Requires-Dist: ruff>=0.1.0; extra == 'dev'
Requires-Dist: safety>=2.0.0; extra == 'dev'
Requires-Dist: twine>=4.0; extra == 'dev'
Provides-Extra: lint
Requires-Dist: bandit[toml]>=1.7.0; extra == 'lint'
Requires-Dist: black>=23.0; extra == 'lint'
Requires-Dist: isort>=5.12; extra == 'lint'
Requires-Dist: mypy>=1.0; extra == 'lint'
Requires-Dist: pip-audit>=2.0.0; extra == 'lint'
Requires-Dist: ruff>=0.1.0; extra == 'lint'
Requires-Dist: safety>=2.0.0; extra == 'lint'
Provides-Extra: test
Requires-Dist: coverage[toml]>=7.0; extra == 'test'
Requires-Dist: pytest-asyncio>=0.21.0; extra == 'test'
Requires-Dist: pytest-cov>=4.0; extra == 'test'
Requires-Dist: pytest>=7.0; extra == 'test'
